MANIFEST.in
setup.py
PGeoMODIS.egg-info/PKG-INFO
PGeoMODIS.egg-info/SOURCES.txt
PGeoMODIS.egg-info/dependency_links.txt
PGeoMODIS.egg-info/requires.txt
PGeoMODIS.egg-info/top_level.txt
pgeomodis/.gitignore
pgeomodis/__init__.py
pgeomodis/config/__init__.py
pgeomodis/config/gaul2modis.py
pgeomodis/config/modis_config.py
pgeomodis/core/__init__.py
pgeomodis/core/modis_core.py
pgeomodis/rest/__init__.py
pgeomodis/rest/modis_rest.py