Metadata-Version: 1.0
Name: PGeoMODIS
Version: 0.1.6
Summary: MODIS plug-in for PGeo.
Home-page: http://pypi.python.org/pypi/PGeoMODIS/
Author: Simone Murzilli; Guido Barbaglia
Author-email: geobrickspy@gmail.com
License: LICENSE.txt
Platform: UNKNOWN
